{
  "personal": {
    "name": "Halimoh Olatunji",
    "title": "Data Analyst | Analytical Problem Solver",
    "subtitle": "Ready to Make an Impact.",
    "about_p1": "My name is Halimoh Olatunji, an aspiring Data Analyst with a strong desire to learn, grow, and bring dedication to the field. I embarked on this journey to transform raw data into actionable insights, helping organizations make smart decisions about the future.",
    "about_p2": "Through rigorous studies and practical project experience, I have built a strong foundation in modern data analysis tools. I am continuously participating in training and virtual experiences to sharpen my critical thinking and problem-solving skills.",
    "cv_link": "./HALIMOH OLATUNJI ACADEMIC CV.pdf",
    "linkedin_link": "https://www.linkedin.com/in/halimoh-temidayo"
  },
  "skills": [
    { "name": "SQL", "percentage": 80 },
    { "name": "Power BI", "percentage": 95 },
    { "name": "Python", "percentage": 70 },
    { "name": "Excel", "percentage": 95 }
  ],
  "expertise_tags": [
    "Data Analysis",
    "Data Visualization",
    "Predictive Modeling",
    "Business Intelligence"
  ],
  "projects": [
      {
      "title": "Customer Mall Segmentation & Clustering",
      "description": "Identifying vital customer groups for targeted marketing. Utilized data analysis and machine learning clustering on demographics and spending behavior.",
      "image_placeholder": "Add Dashboard Screenshot",
      "image_url": "https://alhikmahuniversity.edu.ng/wp-content/uploads/2026/02/ramadan_vc.jpeg",
      "tags": ["Python", "Data Analysis"],
      "link": "https://edinfo.com.ng"
    },
    {
      "title": "NYPD Arrest Data 2022",
      "description": "An exploratory study recognizing patterns and trends in NYC police enforcement activity, examining crime types, dates, locations, and demographics.",
      "image_placeholder": "Add Tableau Screenshot",
      "image_url": "",
      "tags": ["SQL", "Tableau"],
      "link": "#"
    },
    {
      "title": "Supermarket Sales Dashboard",
      "description": "A comprehensive Power BI dashboard providing insights into key metrics like revenue, profit margins, and customer types via interactive visuals.",
      "image_placeholder": "Add Power BI Screenshot",
      "image_url": "",
      "tags": ["Power BI", "Excel"],
      "link": "#"
    }
  ],
  "platforms": [
    {
      "name": "LinkedIn",
      "icon_svg": "<svg class=\"w-8 h-8 text-[#0a66c2] group-hover:bg-[#0a66c2] group-hover:text-white transition-colors rounded\" fill=\"currentColor\" viewBox=\"0 0 24 24\"><path d=\"M19 0h-14c-2.761 0-5 2.239-5 5v14c0 2.761 2.239 5 5 5h14c2.762 0 5-2.239 5-5v-14c0-2.761-2.238-5-5-5zm-11 19h-3v-11h3v11zm-1.5-12.268c-.966 0-1.75-.79-1.75-1.764s.784-1.764 1.75-1.764 1.75.79 1.75 1.764-.783 1.764-1.75 1.764zm13.5 12.268h-3v-5.604c0-3.368-4-3.113-4 0v5.604h-3v-11h3v1.765c1.396-2.586 7-2.777 7 2.476v6.759z\"/></svg>",
      "link": "https://www.linkedin.com/in/halimoh-temidayo"
    },
    {
      "name": "X (Twitter)",
      "icon_svg": "<svg class=\"w-8 h-8 text-black group-hover:scale-110 transition-transform\" fill=\"currentColor\" viewBox=\"0 0 24 24\"><path d=\"M18.901 1.153h3.68l-8.04 9.19L24 22.846h-7.406l-5.8-7.584-6.638 7.584H.474l8.6-9.83L0 1.154h7.594l5.243 6.932ZM17.61 20.644h2.039L6.486 3.24H4.298Z\"/></svg>",
      "link": "https://x.com/Halimoh07_t"
    },
    {
      "name": "Email",
      "icon_svg": "<svg class=\"w-8 h-8 text-rose-500 group-hover:scale-110 transition-transform\" fill=\"none\" stroke=\"currentColor\" stroke-width=\"1.5\" viewBox=\"0 0 24 24\"><path stroke-linecap=\"round\" stroke-linejoin=\"round\" d=\"M21.75 6.75v10.5a2.25 2.25 0 01-2.25 2.25h-15a2.25 2.25 0 01-2.25-2.25V6.75m19.5 0A2.25 2.25 0 0019.5 4.5h-15a2.25 2.25 0 00-2.25 2.25m19.5 0v.243a2.25 2.25 0 01-1.07 1.916l-7.5 4.615a2.25 2.25 0 01-2.36 0L3.32 8.91a2.25 2.25 0 01-1.07-1.916V6.75\"/></svg>",
      "link": "halimaholatunji77@gmail.com?subject=Opportunity%20from%20Portfolio"
    },
    {
      "name": "GitHub",
      "icon_svg": "<svg class=\"w-8 h-8 text-slate-800 group-hover:scale-110 transition-transform\" fill=\"currentColor\" viewBox=\"0 0 24 24\"><path fill-rule=\"evenodd\" clip-rule=\"evenodd\" d=\"M12 2C6.477 2 2 6.477 2 12c0 4.42 2.865 8.166 6.839 9.489.5.092.682-.217.682-.482 0-.237-.008-.866-.013-1.699-2.782.603-3.369-1.34-3.369-1.34-.454-1.156-1.11-1.462-1.11-1.462-.908-.62.069-.608.069-.608 1.003.07 1.531 1.03 1.531 1.03.892 1.529 2.341 1.087 2.91.831.092-.646.35-1.086.636-1.336-2.22-.253-4.555-1.11-4.555-4.943 0-1.091.39-1.984 1.029-2.683-.103-.253-.446-1.27.098-2.647 0 0 .84-.269 2.75 1.025A9.564 9.564 0 0112 6.844c.85.004 1.705.114 2.504.336 1.909-1.294 2.747-1.025 2.747-1.025.546 1.377.203 2.394.1 2.647.64.699 1.028 1.592 1.028 2.683 0 3.842-2.339 4.687-4.566 4.935.359.309.678.919.678 1.852 0 1.336-.012 2.415-.012 2.743 0 .267.18.578.688.48C19.138 20.161 22 16.418 22 12c0-5.523-4.477-10-10-10z\"/></svg>",
      "link": "https://github.com"
    }
  ],
  "achievements": [
    {
      "title": "Microsoft Certified: Power Platform Fundamentals",
      "issuer": "Microsoft",
      "description": "Successfully passed the PL-900 certification, demonstrating expertise in using the Power Platform for low-code solutions, business processes, and data analysis.",
      "link_text": "View Badge &rarr;",
      "link_url": "#"
    },
    {
      "title": "Advanced Data Analytics",
      "issuer": "Bayan Academy supported by J.P. Morgan",
      "description": "Completed a rigorous 15-day advanced program covering SQL, Orange Data mining, and publishing a comprehensive research paper on index crimes.",
      "link_text": "Read Paper &rarr;",
      "link_url": "#"
    },
    {
      "title": "Google Data Analytics Certificate",
      "issuer": "Google / Coursera",
      "description": "Mastered a wide range of data analytics topics including data visualization, statistical analysis, and spreadsheet management, culminating in a capstone project.",
      "link_text": "View Certificate &rarr;",
      "link_url": "#"
    },
    {
      "title": "Power BI in Data Analytics Case Experience",
      "issuer": "PwC Switzerland",
      "description": "Improved data cleaning and visualization techniques, producing extensive dashboards for call center trends, churn analysis, and diversity & inclusion.",
      "link_text": "",
      "link_url": ""
    }
  ],
  "footer": {
    "year": "2026",
    "name": "Halimoh Olatunji"
  }
}
